pymatillion/__init__.py
pymatillion/constants.py
pymatillion/matillion.py
pymatillion-1.0.15.dist-info/LICENSE
pymatillion-1.0.15.dist-info/METADATA
pymatillion-1.0.15.dist-info/WHEEL
pymatillion-1.0.15.dist-info/top_level.txt
pymatillion-1.0.15.dist-info/RECORD
