Metadata-Version: 2.1
Name: pymatillion
Version: 1.0.15
Summary: This is a Python wrapper for interacting with the REST API for Matillion.
Author-email: Abhinav Tiwari <abhinavtiwariusa84@gmail.com>
License: MIT License
Project-URL: Homepage, https://github.com/tiwari-abhi/PyMatillion
Project-URL: Docs, https://tiwari-abhi.github.io/PyMatillion/reference
Keywords: Matillion,ETL,Python
Classifier: License :: OSI Approved :: MIT License
Classifier: Programming Language :: Python
Classifier: Programming Language :: Python :: 3
Classifier: Intended Audience :: Developers
Requires-Python: >=3.10
License-File: LICENSE
Requires-Dist: requests
Provides-Extra: dev
Requires-Dist: black ; extra == 'dev'
Requires-Dist: bumpver ; extra == 'dev'
Requires-Dist: isort ; extra == 'dev'
Requires-Dist: build ; extra == 'dev'
Requires-Dist: twine ; extra == 'dev'
Requires-Dist: mkdocs ; extra == 'dev'
